Metadata-Version: 2.1
Name: fet
Version: 0.0.0.1
Summary: Feature Extraction Toolkit
Home-page: https://github.com/duketemon/fet
Author: Artem Kuchumov
Author-email: kuchumov7@gmail.com
License: BSD License
Keywords: uplift modeling,machine learning,feature extraction,feature engineering
Platform: UNKNOWN
Classifier: Intended Audience :: Science/Research
Classifier: Intended Audience :: Education
Classifier: Programming Language :: Python :: 3
Classifier: Programming Language :: Python :: 3.5
Classifier: Programming Language :: Python :: 3.6
Classifier: Programming Language :: Python :: 3.7
Classifier: Programming Language :: Python :: 3.8
Classifier: Operating System :: OS Independent
Classifier: Topic :: Scientific/Engineering
Classifier: Topic :: Software Development :: Libraries
Classifier: Topic :: Software Development :: Libraries :: Python Modules
Provides-Extra: tests
